{
    "categorie": "Arts",
    "titre": "Romantisme",
    "questions": [
        {
            "titre": "L'école de peinture de Düsseldorf était un mouvement romantique de quel pays ?",
            "choix": [
                [
                    "Espagne",
                    false
                ],
                [
                    "Grande-Bretagne",
                    false
                ],
                [
                    "Russie",
                    false
                ],
                [
                    "Allemagne",
                    true
                ]
            ]
        },
        {
            "titre": "De quel pays François Rude était-il un sculpteur romantique ?",
            "choix": [
                [
                    "Espagne",
                    false
                ],
                [
                    "France",
                    true
                ],
                [
                    "Allemagne",
                    false
                ],
                [
                    "Italie",
                    false
                ]
            ]
        },
        {
            "titre": "William Morris Hunt appartenait à une des familles artistiques de quel pays ?",
            "choix": [
                [
                    "France",
                    false
                ],
                [
                    "Norvège",
                    false
                ],
                [
                    "États-Unis",
                    true
                ],
                [
                    "Grande-Bretagne",
                    false
                ]
            ]
        },
        {
            "titre": "« La Bavaria » a été la première statue colossale à avoir été fondue en quelle matière ?",
            "choix": [
                [
                    "Nickel",
                    false
                ],
                [
                    "Étain",
                    false
                ],
                [
                    "Bronze",
                    true
                ],
                [
                    "Argent",
                    false
                ]
            ]
        },
        {
            "titre": "L'école de Bristol regroupait des peintres influents de quel pays ?",
            "choix": [
                [
                    "L'Espagne",
                    false
                ],
                [
                    "La France",
                    false
                ],
                [
                    "La Suisse",
                    false
                ],
                [
                    "L'Angleterre",
                    true
                ]
            ]
        },
        {
            "titre": "Le monument dédié à Goethe et Schiler est un célèbre point de repère de quel pays ?",
            "choix": [
                [
                    "Roumanie",
                    false
                ],
                [
                    "Pologne",
                    false
                ],
                [
                    "Hongrie",
                    false
                ],
                [
                    "Allemagne",
                    true
                ]
            ]
        },
        {
            "titre": "Outre la sculpture et la peinture, dans quel domaine Honoré Daumier excellait-il ?",
            "choix": [
                [
                    "Poésie",
                    false
                ],
                [
                    "Architecture",
                    false
                ],
                [
                    "Gravure",
                    true
                ],
                [
                    "Musique",
                    false
                ]
            ]
        },
        {
            "titre": "Quel grand artiste a peint le célèbre tableau romantique « La Barque de Dante » ?",
            "choix": [
                [
                    "Girodet",
                    false
                ],
                [
                    "Goya",
                    false
                ],
                [
                    "Delacroix",
                    true
                ],
                [
                    "Turner",
                    false
                ]
            ]
        },
        {
            "titre": "Lequel de ces termes indique l'effet de la lumière dans les paysages ?",
            "choix": [
                [
                    "Néoclassicisme",
                    false
                ],
                [
                    "Symbolisme",
                    false
                ],
                [
                    "Luminisme",
                    true
                ],
                [
                    "Maniérisme",
                    false
                ]
            ]
        },
        {
            "titre": "Quel peintre est célèbre pour sa troublante série des « Peintures noires » ?",
            "choix": [
                [
                    "Corot",
                    false
                ],
                [
                    "Gros",
                    false
                ],
                [
                    "Goya",
                    true
                ],
                [
                    "Füssli",
                    false
                ]
            ]
        },
        {
            "titre": "Dans le mouvement romantique de quel pays l'artiste et poète Carl Spitzweg était-il influent ?",
            "choix": [
                [
                    "Espagne",
                    false
                ],
                [
                    "Royaume-Uni",
                    false
                ],
                [
                    "Italie",
                    false
                ],
                [
                    "Allemagne",
                    true
                ]
            ]
        },
        {
            "titre": "Quel artiste danois a peint « Un groupe d'artistes danois à Rome » ?",
            "choix": [
                [
                    "Bierstadt",
                    false
                ],
                [
                    "Delacroix",
                    false
                ],
                [
                    "Malmström",
                    false
                ],
                [
                    "Hansen",
                    true
                ]
            ]
        },
        {
            "titre": "Quel est le thème des sculptures de Frederic Remington, mêlant romantisme et réalisme ?",
            "choix": [
                [
                    "Animaux",
                    false
                ],
                [
                    "Royauté anglaise",
                    false
                ],
                [
                    "Ouest américain",
                    true
                ],
                [
                    "Mythologie",
                    false
                ]
            ]
        },
        {
            "titre": "Quelle scène le tableau de Turner « Pluie, Vapeur et Vitesse » représente-t-il ?",
            "choix": [
                [
                    "Une usine",
                    false
                ],
                [
                    "Un étang",
                    false
                ],
                [
                    "Un sauna",
                    false
                ],
                [
                    "Une voie ferrée",
                    true
                ]
            ]
        },
        {
            "titre": "Que cherche à apporter à la peinture le mouvement romantique des Nazaréens ?",
            "choix": [
                [
                    "Nature",
                    false
                ],
                [
                    "Spiritualité",
                    true
                ],
                [
                    "Laïcité",
                    false
                ],
                [
                    "Musique",
                    false
                ]
            ]
        },
        {
            "titre": "Quel peintre français est célèbre pour ses lithographies satiriques de la bourgeoisie ?",
            "choix": [
                [
                    "Daumier",
                    true
                ],
                [
                    "Géricault",
                    false
                ],
                [
                    "Fuseli",
                    false
                ],
                [
                    "Delacroix",
                    false
                ]
            ]
        },
        {
            "titre": "En peignant quels sujets Paul Delaroche a-t-il bâti la majorité de sa fortune ?",
            "choix": [
                [
                    "Les chiens",
                    false
                ],
                [
                    "Les enfants",
                    false
                ],
                [
                    "La royauté anglaise",
                    true
                ],
                [
                    "L'Ouest américain",
                    false
                ]
            ]
        },
        {
            "titre": "Sir Charles Barry est célèbre pour son rôle dans la reconstruction de quel palais ?",
            "choix": [
                [
                    "Tintern",
                    false
                ],
                [
                    "Saint-Pierre",
                    false
                ],
                [
                    "Hadrien",
                    false
                ],
                [
                    "Westminster",
                    true
                ]
            ]
        },
        {
            "titre": "Le célèbre « Portrait du duc de Wellington » est représentatif de l'oeuvre de quel peintre ?",
            "choix": [
                [
                    "Hayez",
                    false
                ],
                [
                    "Goya",
                    true
                ],
                [
                    "Danby",
                    false
                ],
                [
                    "Lawrence",
                    false
                ]
            ]
        },
        {
            "titre": "Quel artiste a peint l'émouvant tableau « El tres de mayo de 1808 en Madrid » ?",
            "choix": [
                [
                    "Blake",
                    false
                ],
                [
                    "Goya",
                    true
                ],
                [
                    "Girodet",
                    false
                ],
                [
                    "Mulready",
                    false
                ]
            ]
        }
    ],
    "difficulte": "confirmé"
}