{"categorie": "G\u00e9ographie", "titre": "CULTURE MONDIALE", "questions": [{"titre": "Quelle est la couleur du passeport de l'union europ\u00e9enne d\u00e9livr\u00e9 en Belgique ou en France ?", "choix": [["Verte", false], ["Bordeaux", true], ["Grise", false], ["Bleue", false]]}, {"titre": "Comment appelle-t-on le cachet appos\u00e9 sur un passeport permettant l'entr\u00e9e dans un pays ?", "choix": [["Un permis", false], ["Un code", false], ["Un visa", true], ["Un titre", false]]}, {"titre": "De quel pays le drapeau est-il appel\u00e9 \u00ab\u00a0Union Jack\u00a0\u00bb ou encore \u00ab\u00a0Union Flag\u00a0\u00bb\u00a0par certains ?", "choix": [["La Gr\u00e8ce", false], ["La Suisse", false], ["La Finlande", false], ["La Grande Bretagne", true]]}, {"titre": "Que vous fournira-t-on presque exclusivement pour mettre sur vos frites aux \u00c9tats-Unis ?", "choix": [["De la mayonnaise", false], ["De la tartare", false], ["Du pickles", false], ["Du ketchup", true]]}, {"titre": "Quel est le seul pays d'Europe o\u00f9 certaines voitures ont encore des phares jaunes ?", "choix": [["Portugal", false], ["Gr\u00e8ce", false], ["Belgique", false], ["France", true]]}, {"titre": "Quelle ville est consid\u00e9r\u00e9e par beaucoup comme \u00e9tant le centre diamantaire mondial ?", "choix": [["Mons", false], ["Li\u00e8ge", false], ["Anvers", true], ["Bruxelles", false]]}, {"titre": "Quel fruit du badianier de Chine parfume des boissons comme l'ouzo ou comme l'arak ?", "choix": [["Gingembre", false], ["Anis \u00e9toil\u00e9", true], ["Carvi", false], ["Sel noir", false]]}, {"titre": "Quel est le montant du p\u00e9age de l'autoroute qui relie les villes d'Amsterdam et de Bruxelles ?", "choix": [["27 euros", false], ["19 euros", false], ["Gratuit", true], ["12 euros", false]]}, {"titre": "Vers o\u00f9 regarde-t-on en tout premier lieu avant de traverser une route en Irlande ?", "choix": [["La gauche", false], ["L'arri\u00e8re", false], ["La droite", true], ["L'avant", false]]}, {"titre": "Qu'est-ce qui est turc, n\u00e9 en Autriche et mang\u00e9 en France au petit d\u00e9jeuner ?", "choix": [["Croissant", true], ["Cr\u00eape", false], ["Gaufre", false], ["Pistolet", false]]}], "difficulte": "d\u00e9butant"}